{
  "type": "minecraft:crafting_shapeless",
  "group": "silentcompat",
  "ingredients": [
    {
      "item": "silentcompat:solarmetal_ingot"
    },
    {
      "item": "silentcompat:solarmetal_ingot"
    },
    {
      "item": "silentcompat:solarmetal_ingot"
    },
    {
      "item": "silentcompat:solarmetal_ingot"
    },
    {
      "item": "silentcompat:solarmetal_ingot"
    },
    {
      "item": "silentcompat:solarmetal_ingot"
    },
    {
      "item": "silentcompat:solarmetal_ingot"
    },
    {
      "item": "silentcompat:solarmetal_ingot"
    },
    {
      "item": "silentcompat:solarmetal_ingot"
    }
  ],
  "result": {
    "item": "silentcompat:solarmetal_block"
  }
}