{
    "type": "silentgear:standard",
    "simple": true,
    "availability": {
      "tier": 1,
      "categories": [
        "organic"
      ],
      "visible": true,
      "gear_blacklist": [],
      "can_salvage": true
    },
    "crafting_items": {
      "main": {
        "tag": "silentcompat:bee_stinger"
      }
    },
    "name": {
      "translate": "Bee Stinger"
    },
    "stats": {
      "main": {
        "projectile_speed": 1.1,
        "projectile_accuracy": 1.1
      },
      "tip": {
        "durability": {
          "add": 5.0
        },
        "melee_damage": {
          "add": 1.0
        },
        "ranged_damage": {
          "add": 1.0
        }
      }
    },
    "traits": {
      "main": [
      ],
      "tip": [
        {
          "name": "silentgear:venom",
          "level": 2
        }
      ]
    },
    "model": {
      "tip/all": [
        {
          "texture": "silentgear:tip_sharp",
          "color": "#1a1306"
        }
      ],
      "tip/part": [
        {
          "texture": "silentgear:tip_base"
        },
        {
          "texture": "silentgear:tip",
          "color": "#1a1306"
        },
        {
          "texture": "silentgear:tip_shine"
        }
      ]
    }
  }